LICENSE
MANIFEST.in
README.md
setup.cfg
setup.py
requirements/requirements.txt
src/os_pywf/VERSION
src/os_pywf/__init__.py
src/os_pywf/cmdline.py
src/os_pywf/exceptions.py
src/os_pywf/main.py
src/os_pywf/utils.py
src/os_pywf.egg-info/PKG-INFO
src/os_pywf.egg-info/SOURCES.txt
src/os_pywf.egg-info/dependency_links.txt
src/os_pywf.egg-info/entry_points.txt
src/os_pywf.egg-info/not-zip-safe
src/os_pywf.egg-info/requires.txt
src/os_pywf.egg-info/top_level.txt
src/os_pywf/commands/__init__.py
src/os_pywf/commands/curl.py
src/os_pywf/commands/mysql.py
src/os_pywf/commands/proxy.py
src/os_pywf/commands/redis.py
src/os_pywf/commands/run.py
src/os_pywf/commands/spider.py
src/os_pywf/commands/web.py
src/os_pywf/contrib/__init__.py
src/os_pywf/http/client.py
src/os_pywf/http/web.py
tests/__init__.py
tests/test_version.py